s3_utils/__init__.py
s3_utils/core.py
s3_utils/helpers.py
python_s3_utils-0.1.0.dist-info/AUTHORS.md
python_s3_utils-0.1.0.dist-info/LICENSE
python_s3_utils-0.1.0.dist-info/METADATA
python_s3_utils-0.1.0.dist-info/WHEEL
python_s3_utils-0.1.0.dist-info/top_level.txt
python_s3_utils-0.1.0.dist-info/RECORD
