Metadata-Version: 2.1
Name: python-s3-utils
Version: 0.1.0
Summary: Some simple wrapper functions around boto3 functionality.
Author-email: Tim Santor <tsantor@xstudios.com>
Project-URL: Repository, https://github.com/tsantor/python-s3-utils.git
Project-URL: Issues, https://github.com/tsantor/python-s3-utils/issues
Project-URL: Changelog, https://github.com/tsantor/python-s3-utils/blob/master/HISTORY.md
Classifier: Development Status :: 5 - Production/Stable
Classifier: Environment :: Console
Classifier: Intended Audience :: Developers
Classifier: Natural Language :: English
Classifier: Programming Language :: Python :: 3.8
Classifier: Programming Language :: Python :: 3.9
Classifier: Programming Language :: Python :: 3.10
Classifier: Programming Language :: Python :: 3.11
Classifier: Programming Language :: Python :: 3.12
Requires-Python: >=3.8
License-File: LICENSE
License-File: AUTHORS.md
Requires-Dist: boto3
Provides-Extra: dev
Requires-Dist: moto <6,>=5.0.6 ; extra == 'dev'
